automlst/engine/__init__.py
automlst/engine/data/__init__.py
automlst/engine/data/local/__init__.py
automlst/engine/data/local/csv.py
automlst/engine/data/local/fasta.py
automlst/engine/data/remote/__init__.py
automlst/engine/data/remote/databases/bigsdb.py
automlst/engine/data/structures/__init__.py
automlst/engine/data/structures/genomics.py
automlst/engine/data/structures/mlst.py
automlst/engine/exceptions/database.py
automlst.engine-0.5.2.dist-info/LICENSE
automlst.engine-0.5.2.dist-info/METADATA
automlst.engine-0.5.2.dist-info/WHEEL
automlst.engine-0.5.2.dist-info/top_level.txt
automlst.engine-0.5.2.dist-info/RECORD
