Metadata-Version: 2.2
Name: automlst.engine
Version: 0.5.2
Summary: A library to rapidly fetch fetch MLST profiles given sequences for various diseases.
Requires-Python: >=3.11
License-File: LICENSE
Requires-Dist: biopython
Requires-Dist: aiohttp[speedups]
